MANIFEST.in
README.rst
requirements.txt
setup.py
test_requirements.txt
py_raildriver.egg-info/PKG-INFO
py_raildriver.egg-info/SOURCES.txt
py_raildriver.egg-info/dependency_links.txt
py_raildriver.egg-info/not-zip-safe
py_raildriver.egg-info/requires.txt
py_raildriver.egg-info/top_level.txt
raildriver/__init__.py
raildriver/events.py
raildriver/library.py