Metadata-Version: 1.1
Name: py-raildriver
Version: 1.1.6
Summary: Python interface to Train Simulator 2016
Home-page: https://github.com/centralniak/py-raildriver
Author: Piotr Kilczuk
Author-email: piotr@tymaszweb.pl
License: MIT License
Platform: Windows
Classifier: Development Status :: 5 - Production/Stable
Classifier: Intended Audience :: Developers
Classifier: License :: OSI Approved :: MIT License
Classifier: Operating System :: Microsoft :: Windows
Classifier: Programming Language :: Python
Classifier: Topic :: Software Development :: Libraries
